wxyz/jsonld/__init__.py
wxyz/jsonld/_version.py
wxyz/jsonld/base.py
wxyz/jsonld/install.json
wxyz/jsonld/widget_jsonld.py
wxyz/jsonld/js/LICENSE.txt
wxyz/jsonld/js/README.md
wxyz/jsonld/js/package.json
wxyz/jsonld/labextension/package.json
wxyz/jsonld/labextension/static/248.0c17c5d2c6a21c53aee8.js
wxyz/jsonld/labextension/static/333.2a2cd69664c8bc864dc0.js
wxyz/jsonld/labextension/static/568.1d1f62fb5bee4078005c.js
wxyz/jsonld/labextension/static/866.21586f014a2d9f8aedc1.js
wxyz/jsonld/labextension/static/971.62c9b9e6ba4e409bedd2.js
wxyz/jsonld/labextension/static/971.62c9b9e6ba4e409bedd2.js.LICENSE.txt
wxyz/jsonld/labextension/static/remoteEntry.9bf7837a87ff10acfb66.js
wxyz/jsonld/labextension/static/style.js
wxyz_jsonld-0.5.1.data/data/share/jupyter/labextensions/@deathbeds/wxyz-jsonld/install.json
wxyz_jsonld-0.5.1.data/data/share/jupyter/labextensions/@deathbeds/wxyz-jsonld/package.json
wxyz_jsonld-0.5.1.data/data/share/jupyter/labextensions/@deathbeds/wxyz-jsonld/static/248.0c17c5d2c6a21c53aee8.js
wxyz_jsonld-0.5.1.data/data/share/jupyter/labextensions/@deathbeds/wxyz-jsonld/static/333.2a2cd69664c8bc864dc0.js
wxyz_jsonld-0.5.1.data/data/share/jupyter/labextensions/@deathbeds/wxyz-jsonld/static/568.1d1f62fb5bee4078005c.js
wxyz_jsonld-0.5.1.data/data/share/jupyter/labextensions/@deathbeds/wxyz-jsonld/static/866.21586f014a2d9f8aedc1.js
wxyz_jsonld-0.5.1.data/data/share/jupyter/labextensions/@deathbeds/wxyz-jsonld/static/971.62c9b9e6ba4e409bedd2.js
wxyz_jsonld-0.5.1.data/data/share/jupyter/labextensions/@deathbeds/wxyz-jsonld/static/971.62c9b9e6ba4e409bedd2.js.LICENSE.txt
wxyz_jsonld-0.5.1.data/data/share/jupyter/labextensions/@deathbeds/wxyz-jsonld/static/remoteEntry.9bf7837a87ff10acfb66.js
wxyz_jsonld-0.5.1.data/data/share/jupyter/labextensions/@deathbeds/wxyz-jsonld/static/style.js
wxyz_jsonld-0.5.1.dist-info/LICENSE.txt
wxyz_jsonld-0.5.1.dist-info/METADATA
wxyz_jsonld-0.5.1.dist-info/WHEEL
wxyz_jsonld-0.5.1.dist-info/top_level.txt
wxyz_jsonld-0.5.1.dist-info/RECORD
